azure/healthinsights/radiologyinsights/__init__.py
azure/healthinsights/radiologyinsights/_client.py
azure/healthinsights/radiologyinsights/_configuration.py
azure/healthinsights/radiologyinsights/_model_base.py
azure/healthinsights/radiologyinsights/_patch.py
azure/healthinsights/radiologyinsights/_serialization.py
azure/healthinsights/radiologyinsights/_types.py
azure/healthinsights/radiologyinsights/_vendor.py
azure/healthinsights/radiologyinsights/_version.py
azure/healthinsights/radiologyinsights/py.typed
azure/healthinsights/radiologyinsights/_operations/__init__.py
azure/healthinsights/radiologyinsights/_operations/_operations.py
azure/healthinsights/radiologyinsights/_operations/_patch.py
azure/healthinsights/radiologyinsights/_utils/__init__.py
azure/healthinsights/radiologyinsights/_utils/model_base.py
azure/healthinsights/radiologyinsights/_utils/serialization.py
azure/healthinsights/radiologyinsights/_utils/utils.py
azure/healthinsights/radiologyinsights/aio/__init__.py
azure/healthinsights/radiologyinsights/aio/_client.py
azure/healthinsights/radiologyinsights/aio/_configuration.py
azure/healthinsights/radiologyinsights/aio/_patch.py
azure/healthinsights/radiologyinsights/aio/_vendor.py
azure/healthinsights/radiologyinsights/aio/_operations/__init__.py
azure/healthinsights/radiologyinsights/aio/_operations/_operations.py
azure/healthinsights/radiologyinsights/aio/_operations/_patch.py
azure/healthinsights/radiologyinsights/models/__init__.py
azure/healthinsights/radiologyinsights/models/_enums.py
azure/healthinsights/radiologyinsights/models/_models.py
azure/healthinsights/radiologyinsights/models/_patch.py
azure_healthinsights_radiologyinsights-1.1.0.dist-info/LICENSE
azure_healthinsights_radiologyinsights-1.1.0.dist-info/METADATA
azure_healthinsights_radiologyinsights-1.1.0.dist-info/WHEEL
azure_healthinsights_radiologyinsights-1.1.0.dist-info/top_level.txt
azure_healthinsights_radiologyinsights-1.1.0.dist-info/RECORD
